UrlUsefullness/__init__.py
UrlUsefullness-0.0.1.dist-info/METADATA
UrlUsefullness-0.0.1.dist-info/WHEEL
UrlUsefullness-0.0.1.dist-info/top_level.txt
UrlUsefullness-0.0.1.dist-info/RECORD
