Metadata-Version: 2.1
Name: UrlUsefullness
Version: 0.0.1
Summary: A simple package made for URLs. Credits: Url91
Home-page: https://github.com
Author: Dev
Author-email: example@example.com
License: UNKNOWN
Platform: UNKNOWN
Classifier: Programming Language :: Python :: 3
Classifier: License :: OSI Approved :: MIT License
Classifier: Operating System :: OS Independent
